jupyter_resource_usage_proxy/__init__.py
jupyter_resource_usage_proxy/app.py
jupyter_resource_usage_proxy/handlers.py
jupyter_resource_usage_proxy-0.1.2.data/data/etc/jupyter/jupyter_server_config.d/jupyter_resource_usage_proxy.json
jupyter_resource_usage_proxy-0.1.2.dist-info/METADATA
jupyter_resource_usage_proxy-0.1.2.dist-info/WHEEL
jupyter_resource_usage_proxy-0.1.2.dist-info/licenses/LICENSE
jupyter_resource_usage_proxy-0.1.2.dist-info/RECORD
