Metadata-Version: 2.3
Name: jupyter_resource_usage_proxy
Version: 0.1.2
Summary: A Jupyter Server Extension Proxying Resource Usage.
Project-URL: Homepage, https://github.com/davidbrochart/jupyter_resource_usage_proxy
Author-email: David Brochart <david.brochart@gmail.com>
License: MIT License
License-File: LICENSE
Keywords: ipython,jupyter
Classifier: Intended Audience :: Developers
Classifier: Intended Audience :: Science/Research
Classifier: Intended Audience :: System Administrators
Classifier: License :: OSI Approved :: MIT License
Classifier: Programming Language :: Python
Classifier: Programming Language :: Python :: 3.8
Classifier: Programming Language :: Python :: 3.9
Classifier: Programming Language :: Python :: 3.10
Classifier: Programming Language :: Python :: 3.11
Classifier: Programming Language :: Python :: 3.12
Requires-Python: >=3.8
Requires-Dist: httpx<0.28,>=0.27.0
Requires-Dist: jupyter-server<3.0.0,>=1.0.0
